kwb_loader/__init__.py
kwb_loader/loader.py
kwb_loader-0.3.2.dist-info/METADATA
kwb_loader-0.3.2.dist-info/WHEEL
kwb_loader-0.3.2.dist-info/RECORD
