Metadata-Version: 2.1
Name: kwb-loader
Version: 0.3.2
Summary: 
Author: Your Name
Author-email: you@example.com
Requires-Python: >=3.10,<4.0
Classifier: Programming Language :: Python :: 3
Classifier: Programming Language :: Python :: 3.10
Classifier: Programming Language :: Python :: 3.11
Classifier: Programming Language :: Python :: 3.12
Requires-Dist: numpy (==2.0.0)
Requires-Dist: polars (>=1.9.0,<2.0.0)
Requires-Dist: psycopg2-binary (==2.9.9)
